sauth.py
sauth-1.1.0.dist-info/entry_points.txt
sauth-1.1.0.dist-info/LICENSE
sauth-1.1.0.dist-info/WHEEL
sauth-1.1.0.dist-info/METADATA
sauth-1.1.0.dist-info/RECORD
