Metadata-Version: 2.1
Name: sauth
Version: 1.1.0
Summary: simple server for serving directories via http or https and BASIC authorization
Home-page: https://github.com/Granitosaurus/sauth/
License: GPL-3.0-or-later
Keywords: http,server,authentication
Author: granitosaurus
Author-email: bernardas.alisauskas@pm.me
Requires-Python: >=3.6,<4.0
Classifier: Intended Audience :: Developers
Classifier: License :: OSI Approved :: GNU General Public License v3 or later (GPLv3+)
Classifier: Natural Language :: English
Classifier: Programming Language :: Python :: 3
Classifier: Programming Language :: Python :: 3.10
Classifier: Programming Language :: Python :: 3.6
Classifier: Programming Language :: Python :: 3.7
Classifier: Programming Language :: Python :: 3.8
Classifier: Programming Language :: Python :: 3.9
Requires-Dist: click (>=8.0.3,<9.0.0)
Project-URL: Repository, https://github.com/Granitosaurus/sauth/
